README.rst
setup.py
bin/__init__.py
bin/create_files.py
openformats/__init__.py
openformats/exceptions.py
openformats/handlers.py
openformats/strings.py
openformats/transcribers.py
openformats.egg-info/PKG-INFO
openformats.egg-info/SOURCES.txt
openformats.egg-info/dependency_links.txt
openformats.egg-info/requires.txt
openformats.egg-info/top_level.txt
openformats/formats/__init__.py
openformats/formats/android.py
openformats/formats/beta_android.py
openformats/formats/json.py
openformats/formats/plaintext.py
openformats/formats/po.py
openformats/formats/srt.py
openformats/formats/stringsdict.py
openformats/tests/__init__.py
openformats/tests/run_tests.py
openformats/tests/test_handlers.py
openformats/tests/test_strings.py
openformats/tests/formats/__init__.py
openformats/tests/formats/android/__init__.py
openformats/tests/formats/android/test_android.py
openformats/tests/formats/beta_android/__init__.py
openformats/tests/formats/beta_android/test_android.py
openformats/tests/formats/beta_keyvaluejson/__init__.py
openformats/tests/formats/beta_keyvaluejson/test_json.py
openformats/tests/formats/common/__init__.py
openformats/tests/formats/plaintext/__init__.py
openformats/tests/formats/plaintext/test_plaintext.py
openformats/tests/formats/po/__init__.py
openformats/tests/formats/po/test_po.py
openformats/tests/formats/srt/__init__.py
openformats/tests/formats/srt/test_srt.py
openformats/tests/formats/stringsdict/__init__.py
openformats/tests/formats/stringsdict/test_stringsdict.py
openformats/tests/util_tests/__init__.py
openformats/tests/util_tests/test_json.py
openformats/tests/util_tests/test_xml.py
openformats/tests/utils/__init__.py
openformats/tests/utils/dictionary.py
openformats/tests/utils/strings.py
openformats/utils/__init__.py
openformats/utils/compilers.py
openformats/utils/json.py
openformats/utils/xml.py
openformats/utils/xmlutils.py
testbed/main/__init__.py
testbed/main/models.py
testbed/main/tests.py
testbed/main/urls.py
testbed/main/views.py