Metadata-Version: 1.0
Name: openformats
Version: 0.0.34
Summary: The Transifex Open Formats library
Home-page: https://github.com/transifex/openformats
Author: Transifex
Author-email: support@transifex.com
License: UNKNOWN
Platform: UNKNOWN
